tiddl/__init__.py
tiddl/cli/__init__.py
tiddl/cli/app.py
tiddl/cli/config.py
tiddl/cli/const.py
tiddl/cli/ctx.py
tiddl/cli/commands/__init__.py
tiddl/cli/commands/auth.py
tiddl/cli/commands/export.py
tiddl/cli/commands/download/__init__.py
tiddl/cli/commands/download/downloader.py
tiddl/cli/commands/download/output.py
tiddl/cli/commands/subcommands/__init__.py
tiddl/cli/commands/subcommands/fav.py
tiddl/cli/commands/subcommands/url.py
tiddl/cli/utils/__init__.py
tiddl/cli/utils/download.py
tiddl/cli/utils/resource.py
tiddl/cli/utils/auth/__init__.py
tiddl/cli/utils/auth/core.py
tiddl/cli/utils/auth/models.py
tiddl/core/__init__.py
tiddl/core/api/__init__.py
tiddl/core/api/api.py
tiddl/core/api/client.py
tiddl/core/api/exceptions.py
tiddl/core/api/models/__init__.py
tiddl/core/api/models/base.py
tiddl/core/api/models/resources.py
tiddl/core/api/models/review.py
tiddl/core/auth/__init__.py
tiddl/core/auth/api.py
tiddl/core/auth/client.py
tiddl/core/auth/exceptions.py
tiddl/core/auth/models.py
tiddl/core/metadata/__init__.py
tiddl/core/metadata/cover.py
tiddl/core/metadata/track.py
tiddl/core/metadata/video.py
tiddl/core/utils/__init__.py
tiddl/core/utils/const.py
tiddl/core/utils/download.py
tiddl/core/utils/ffmpeg.py
tiddl/core/utils/format.py
tiddl/core/utils/m3u.py
tiddl/core/utils/parse.py
tiddl/core/utils/sanitize.py
tiddl-3.2.0.dist-info/licenses/LICENSE
tiddl-3.2.0.dist-info/METADATA
tiddl-3.2.0.dist-info/WHEEL
tiddl-3.2.0.dist-info/entry_points.txt
tiddl-3.2.0.dist-info/top_level.txt
tiddl-3.2.0.dist-info/RECORD
