Metadata-Version: 2.4
Name: tiddl
Version: 3.2.0
Summary: Download Tidal tracks with CLI downloader.
Author: oskvr37
Project-URL: homepage, https://github.com/oskvr37/tiddl
Classifier: Environment :: Console
Classifier: Programming Language :: Python :: 3
Classifier: Operating System :: OS Independent
Requires-Python: >=3.13
License-File: LICENSE
Requires-Dist: aiofiles>=25.1.0
Requires-Dist: aiohttp>=3.13.2
Requires-Dist: m3u8>=6.0.0
Requires-Dist: mutagen>=1.47.0
Requires-Dist: pydantic>=2.12.4
Requires-Dist: requests>=2.32.5
Requires-Dist: requests-cache>=1.2.1
Requires-Dist: typer>=0.20.0
Dynamic: license-file
